audmetric/__init__.py
audmetric/core/__init__.py
audmetric/core/api.py
audmetric/core/utils.py
audmetric/utils/__init__.py
audmetric-1.3.1.dist-info/licenses/LICENSE
docs/changelog.rst
docs/conf.py
docs/contributing.rst
docs/genindex.rst
docs/index.rst
docs/install.rst
docs/refs.bib
docs/_templates/autosummary/base.rst
docs/_templates/autosummary/class.rst
docs/_templates/autosummary/function.rst
docs/api-src/audmetric.rst
docs/api-src/audmetric.utils.rst
tests/test_api.py
tests/test_concordance_cc.py
tests/test_error_rates.py
tests/test_event_based.py
tests/test_linkability.py
tests/test_utils.py
tests/assets/error_rates/README.md
tests/assets/error_rates/error_rates_reference.py
tests/assets/error_rates/der/0/prediction.csv
tests/assets/error_rates/der/0/result.csv
tests/assets/error_rates/der/0/truth.csv
tests/assets/error_rates/der/1/prediction.csv
tests/assets/error_rates/der/1/result.csv
tests/assets/error_rates/der/1/truth.csv
tests/assets/error_rates/der/2/prediction.csv
tests/assets/error_rates/der/2/result.csv
tests/assets/error_rates/der/2/truth.csv
tests/assets/error_rates/der/3/prediction.csv
tests/assets/error_rates/der/3/result.csv
tests/assets/error_rates/der/3/truth.csv
tests/assets/error_rates/der/4/prediction.csv
tests/assets/error_rates/der/4/result.csv
tests/assets/error_rates/der/4/truth.csv
tests/assets/error_rates/ier/0/prediction.csv
tests/assets/error_rates/ier/0/result.csv
tests/assets/error_rates/ier/0/truth.csv
tests/assets/error_rates/ier/1/prediction.csv
tests/assets/error_rates/ier/1/result.csv
tests/assets/error_rates/ier/1/truth.csv
tests/assets/error_rates/ier/2/prediction.csv
tests/assets/error_rates/ier/2/result.csv
tests/assets/error_rates/ier/2/truth.csv
tests/assets/error_rates/ier/3/prediction.csv
tests/assets/error_rates/ier/3/result.csv
tests/assets/error_rates/ier/3/truth.csv
tests/assets/error_rates/ier/4/prediction.csv
tests/assets/error_rates/ier/4/result.csv
tests/assets/error_rates/ier/4/truth.csv
tests/assets/event_based/README.md
audmetric-1.3.1.dist-info/METADATA
audmetric-1.3.1.dist-info/WHEEL
audmetric-1.3.1.dist-info/top_level.txt
audmetric-1.3.1.dist-info/RECORD
