Metadata-Version: 2.4
Name: audmetric
Version: 1.3.1
Summary: Evaluate machine-learning models
Author: Johannes Wagner, Stephan Huber, Andreas Triantafyllopoulos
Author-email: Hagen Wierstorf <hwierstorf@audeering.com>, Uwe Reichel <ureichel@audeering.com>, Maximilian Schmitt <mschmitt@audeering.com>
License-Expression: MIT
Project-URL: repository, https://github.com/audeering/audmetric/
Project-URL: documentation, https://audeering.github.io/audmetric/
Keywords: mlops,machine learning
Classifier: Development Status :: 5 - Production/Stable
Classifier: Intended Audience :: Science/Research
Classifier: Intended Audience :: Developers
Classifier: Operating System :: OS Independent
Classifier: Programming Language :: Python
Classifier: Programming Language :: Python :: 3
Classifier: Programming Language :: Python :: 3.10
Classifier: Programming Language :: Python :: 3.11
Classifier: Programming Language :: Python :: 3.12
Classifier: Programming Language :: Python :: 3.13
Classifier: Programming Language :: Python :: 3.14
Classifier: Topic :: Scientific/Engineering
Requires-Python: >=3.10
License-File: LICENSE
Requires-Dist: audeer>=1.1.0
Requires-Dist: numpy
Dynamic: license-file
